my_package/__init__.py
my_package/my_code.py
ste2_my_project-0.0.1.dist-info/METADATA
ste2_my_project-0.0.1.dist-info/WHEEL
ste2_my_project-0.0.1.dist-info/top_level.txt
ste2_my_project-0.0.1.dist-info/RECORD
